xigt/__about__.py
xigt/__init__.py
xigt/consts.py
xigt/errors.py
xigt/main.py
xigt/metadata.py
xigt/mixins.py
xigt/model.py
xigt/query.py
xigt/ref.py
xigt/xigtpath.py
xigt/codecs/__init__.py
xigt/codecs/xigtjson.py
xigt/codecs/xigtxml.py
xigt/exporters/__init__.py
xigt/exporters/itsdb.py
xigt/exporters/latex.py
xigt/exporters/util.py
xigt/importers/__init__.py
xigt/importers/odin.py
xigt/importers/toolbox.py
xigt/scripts/__init__.py
xigt/scripts/xigt_export.py
xigt/scripts/xigt_import.py
xigt/scripts/xigt_partition.py
xigt/scripts/xigt_process.py
xigt/scripts/xigt_query.py
xigt/scripts/xigt_sort.py
xigt/scripts/xigt_validate.py
Xigt-1.1.1.dist-info/LICENSE
Xigt-1.1.1.dist-info/METADATA
Xigt-1.1.1.dist-info/WHEEL
Xigt-1.1.1.dist-info/entry_points.txt
Xigt-1.1.1.dist-info/top_level.txt
Xigt-1.1.1.dist-info/RECORD
