Metadata-Version: 2.1
Name: Xigt
Version: 1.1.1
Summary: A framework for eXtensible Interlinear Glossed Text
Home-page: https://github.com/xigt/xigt
Author: Michael Wayne Goodman
Author-email: goodman.m.w@gmail.com
License: MIT
Keywords: nlp igt linguistics
Platform: UNKNOWN
Classifier: Development Status :: 5 - Production/Stable
Classifier: Environment :: Console
Classifier: Intended Audience :: Developers
Classifier: Intended Audience :: Information Technology
Classifier: Intended Audience :: Science/Research
Classifier: License :: OSI Approved :: MIT License
Classifier: Programming Language :: Python :: 3
Classifier: Programming Language :: Python :: 3.6
Classifier: Programming Language :: Python :: 3.7
Classifier: Programming Language :: Python :: 3.8
Classifier: Programming Language :: Python :: 3.9
Classifier: Topic :: Scientific/Engineering :: Information Analysis
Classifier: Topic :: Software Development :: Libraries :: Python Modules
Classifier: Topic :: Text Processing :: Linguistic
Provides-Extra: dev
Requires-Dist: pytest ; extra == 'dev'
